README.md
setup.cfg
setup.py
jc_dsnd_distributions/Binomialdistribution.py
jc_dsnd_distributions/Gaussiandistribution.py
jc_dsnd_distributions/Generaldistribution.py
jc_dsnd_distributions/__init__.py
jc_dsnd_distributions.egg-info/PKG-INFO
jc_dsnd_distributions.egg-info/SOURCES.txt
jc_dsnd_distributions.egg-info/dependency_links.txt
jc_dsnd_distributions.egg-info/not-zip-safe
jc_dsnd_distributions.egg-info/top_level.txt