Metadata-Version: 1.0
Name: jc-dsnd-distributions
Version: 0.1
Summary: Gaussian distributions
Home-page: UNKNOWN
Author: Juan Caio
Author-email: juancaiops@gmail.com
License: UNKNOWN
Platform: UNKNOWN
